imgurfy/__init__.py
imgurfy/imgurfy.py
imgurfy-0.0.2.dist-info/LICENSE
imgurfy-0.0.2.dist-info/METADATA
imgurfy-0.0.2.dist-info/WHEEL
imgurfy-0.0.2.dist-info/entry_points.txt
imgurfy-0.0.2.dist-info/top_level.txt
imgurfy-0.0.2.dist-info/RECORD
