Metadata-Version: 2.1
Name: imgurfy
Version: 0.0.2
Summary: Simple CLI for Imgur API
Home-page: https://github.com/samapriya/imgurfy
Author: Samapriya Roy
Author-email: samapriya.roy@gmail.com
License: Apache 2.0
Platform: UNKNOWN
Classifier: Intended Audience :: Developers
Classifier: Intended Audience :: Science/Research
Classifier: Natural Language :: English
Classifier: License :: OSI Approved :: MIT License
Classifier: Programming Language :: Python :: 3.6
Classifier: Programming Language :: Python :: 3.7
Classifier: Operating System :: OS Independent
Classifier: Topic :: Multimedia :: Graphics
Requires-Dist: logzero (>=1.5.0)
Requires-Dist: requests (==2.27.1)
